{
  "categories": [
    {
      "id": 1,
      "name": "Mì Gói"
    },
    {
      "id": 2,
      "name": "Mì Ly"
    },
    {
      "id": 3,
      "name": "Mì Tô"
    }
  ],
  "products": [
    {
      "id": 1,
      "name": "Hảo Hảo Tôm Chua Cay",
      "cate_id": 1,
      "price": 5000,
      "detail": "Trải nghiệm hương vị cay nồng của Hảo Hảo Tôm Chua Cay. Một sự kết hợp hấp dẫn giữa chua và cay sẽ khiến nốt ruột của bạn mong đợi thêm.",
      "image": "HH_TCC.png"
    },
    {
      "id": 2,
      "name": "Hảo Hảo Lẩu Kim Chi",
      "cate_id": 1,
      "price": 6000,
      "detail": "Thưởng thức hương vị ngon miệng của Hảo Hảo Lẩu Kim Chi. Một món xào độc đáo kết hợp sự giàu chất của kim chi với hương vị ngon của mì Hảo Hảo, tạo nên một trải nghiệm ẩm thực đầy thú vị.",
      "image": "HH_LauKC_HQ.png"
    },
    {
      "id": 3,
      "name": "Hảo Hảo Mì Xào Chua Ngọt",
      "cate_id": 1,
      "price": 7000,
      "detail": "Nếm thử sự cân bằng hoàn hảo giữa ngọt và chua với Hảo Hảo Mì Xào Chua Ngọt. Một biểu tượng của hương vị biển cả sẽ đưa bạn đến một thế giới của niềm hạnh phúc ẩm thực.",
      "image": "HH_MX_Chuangot.png"
    },
    {
      "id": 4,
      "name": "Hảo Hảo Sa Tế Hành Tím",
      "cate_id": 1,
      "price": 8000,
      "detail": "Thưởng thức Hảo Hảo Sa Tế Hành Tím. Một sự kết hợp ngon miệng giữa vị cay của ớt Sa Tế và hương thơm của nấm Kim Châm sẽ khiến bạn say mê.",
      "image": "HH_STHT.png"
    },
    {
      "id": 5,
      "name": "Ly Hảo Hảo Thịt Bò Bằm",
      "cate_id": 2,
      "price": 7500,
      "detail": "Hương vị tuyệt vời của Ly Hảo Hảo Thịt Bò Bằm. Một trải nghiệm ẩm thực độc đáo, kết hợp giữa thịt bò bằm và hương vị cay của Gà Cay Hảo Hảo.",
      "image": "Ly-ThitHamBiDo.png"
    },
    {
      "id": 6,
      "name": "Ly Hảo Hảo Chay",
      "cate_id": 2,
      "price": 8500,
      "detail": "Dấu ấn của hương vị chay với Ly Hảo Hảo Chay. Một sự hòa quyện của mì Quảng Hảo Hảo sẽ khiến bạn đắm chìm trong hương vị truyền thống.",
      "image": "LY-CHAY.png"
    },
    {
      "id": 7,
      "name": "Ly Hảo Hảo Tôm Chua Cay",
      "cate_id": 2,
      "price": 9000,
      "detail": "Ly Hảo Hảo Tôm Chua Cay - Sự hòa quyện của hương vị tôm hùm đặc trưng. Một trải nghiệm ẩm thực đẳng cấp với hương vị tinh tế của Hảo Hảo.",
      "image": "Ly-TomChuaCay.png"
    },
    {
      "id": 8,
      "name": "Ly Hảo Hảo TomYum",
      "cate_id": 2,
      "price": 9500,
      "detail": "Ly Hảo Hảo TomYum - Hương vị thơm ngon của canh TomYum. Một sự kết hợp tinh tế giữa hương vị cay cay và thơm ngon của Bò Khô Hảo Hảo.",
      "image": "Ly-TomYum.png"
    }
  ],

  "orders": [
    {
      "id": 1,
      "customer_name": "John Doe",
      "customer_address": "123 Main St",
      "customer_email": "john.doe@example.com",
      "customer_phone_number": "0123-456-790",
      "created_date": "2024-01-12",
      "status": "Đang xử lí"
    },
    {
      "id": 2,
      "customer_name": "Jane Smith",
      "customer_address": "456 Oak St",
      "customer_email": "jane.smith@example.com",
      "customer_phone_number": "0987-654-320",
      "created_date": "2024-01-13",
      "status": "Đang giao"
    }
  ],
  "order_details": [
    {
      "order_id": 1,
      "product_id": 1,
      "quantity": 2,
      "unit_price": 10000
    },
    {
      "order_id": 1,
      "product_id": 2,
      "quantity": 1,
      "unit_price": 6000
    }
  ]
}
